mk_pass-0.1.2.dist-info/METADATA
mk_pass-0.1.2.dist-info/WHEEL
mk_pass-0.1.2.dist-info/entry_points.txt
mk_pass/__init__.py
mk_pass/__init__.pyi
mk_pass/mk_pass.abi3.so
mk_pass/py.typed
mk_pass-0.1.2.dist-info/RECORD
