Metadata-Version: 2.4
Name: mk-pass
Version: 0.1.2
Classifier: Development Status :: 5 - Production/Stable
Classifier: Intended Audience :: Developers
Classifier: Intended Audience :: System Administrators
Classifier: Intended Audience :: Information Technology
Classifier: Natural Language :: English
Classifier: Operating System :: Microsoft :: Windows
Classifier: Operating System :: POSIX :: Linux
Classifier: Operating System :: MacOS
Classifier: Programming Language :: Python :: 3
Classifier: Topic :: Software Development :: Build Tools
Classifier: Programming Language :: Rust
Classifier: Programming Language :: Python :: Implementation :: CPython
Classifier: Programming Language :: Python :: Implementation :: PyPy
Requires-Dist: pytest==8.4.2 ; extra == 'test'
Provides-Extra: test
Summary: A comprehensive password generator.
Keywords: password,generator,random,comprehensive,rust
Author-email: Brendan Doherty <2bndy5@gmail.com>
License: MIT License
Requires-Python: >=3.9
Project-URL: source, https://github.com/2bndy5/mk-pass
Project-URL: tracker, https://github.com/2bndy5/mk-pass/issues
